DeepSlice/__init__.py
DeepSlice/main.py
DeepSlice/coord_post_processing/__init__.py
DeepSlice/coord_post_processing/angle_methods.py
DeepSlice/coord_post_processing/depth_estimation.py
DeepSlice/coord_post_processing/spacing_and_indexing.py
DeepSlice/coord_post_processing/plane_alignment_functions/__init__.py
DeepSlice/coord_post_processing/plane_alignment_functions/plane_alignment.py
DeepSlice/metadata/__init__.py
DeepSlice/metadata/config.json
DeepSlice/metadata/metadata_loader.py
DeepSlice/metadata/volumes/placeholder.txt
DeepSlice/metadata/weights/placeholder.txt
DeepSlice/neural_network/__init__.py
DeepSlice/neural_network/network_architecture.py
DeepSlice/neural_network/neural_network.py
DeepSlice/read_and_write/QuickNII_functions.py
DeepSlice/read_and_write/__init__.py
deepslice-1.2.6.dist-info/licenses/LICENSE
deepslice-1.2.6.dist-info/METADATA
deepslice-1.2.6.dist-info/WHEEL
deepslice-1.2.6.dist-info/top_level.txt
deepslice-1.2.6.dist-info/RECORD
