Metadata-Version: 2.4
Name: DeepSlice
Version: 1.2.6
Summary: A package to align histology to 3D brain atlases
Home-page: https://github.com/PolarBean/DeepSlice
Download-URL: https://github.com/PolarBean/DeepSlice/archive/refs/tags/1.2.6.tar.gz
Author: DeepSlice Team
Author-email: harry.carey@medisin.uio.no
License: GPL-3.0
Keywords: histology,brain,atlas,alignment
Classifier: Development Status :: 5 - Production/Stable
Classifier: Intended Audience :: Science/Research
Classifier: Topic :: Scientific/Engineering :: Bio-Informatics
Classifier: License :: OSI Approved :: GNU General Public License v3 (GPLv3)
Classifier: Programming Language :: Python
Requires-Python: >=3.7,<3.13
License-File: LICENSE
Requires-Dist: numpy
Requires-Dist: scikit-learn
Requires-Dist: scikit-image
Requires-Dist: tensorflow
Requires-Dist: h5py
Requires-Dist: typing
Requires-Dist: pandas
Requires-Dist: requests
Requires-Dist: protobuf
Requires-Dist: lxml
Requires-Dist: urllib3==1.26.6
Dynamic: author
Dynamic: author-email
Dynamic: classifier
Dynamic: description
Dynamic: description-content-type
Dynamic: download-url
Dynamic: home-page
Dynamic: keywords
Dynamic: license
Dynamic: license-file
Dynamic: requires-dist
Dynamic: requires-python
Dynamic: summary
